groundinggrid/__init__.py
groundinggrid-0.1.1.dist-info/LICENSE
groundinggrid-0.1.1.dist-info/METADATA
groundinggrid-0.1.1.dist-info/WHEEL
groundinggrid-0.1.1.dist-info/RECORD
