Metadata-Version: 2.1
Name: groundinggrid
Version: 0.1.1
Summary: Grounding Grid
Author: Filip Dimitrovski
Author-email: filip.dimitrovski@visiocue.com
Requires-Python: >=3.9,<4.0
Classifier: Programming Language :: Python :: 3
Classifier: Programming Language :: Python :: 3.9
Classifier: Programming Language :: Python :: 3.10
Classifier: Programming Language :: Python :: 3.11
Classifier: Programming Language :: Python :: 3.12
Classifier: Programming Language :: Python :: 3.13
Requires-Dist: Pillow
Requires-Dist: fastapi
Requires-Dist: google-generativeai
Requires-Dist: numpy
Requires-Dist: openai
Requires-Dist: pytest-benchmark
Requires-Dist: tqdm
